Metadata-Version: 2.1
Name: odoo-addon-web_company_color
Version: 18.0.1.0.4
Requires-Python: >=3.10
Requires-Dist: odoo==18.0.*
Summary: Web Company Color
Home-page: https://github.com/OCA/web
License: AGPL-3
Author: =?utf-8?q?Alexandre_D=C3=ADaz=2C_Odoo_Community_Association_=28OCA=29?=
Author-email: support@odoo-community.org
Classifier: Programming Language :: Python
Classifier: Framework :: Odoo
Classifier: Framework :: Odoo :: 18.0
Classifier: License :: OSI Approved :: GNU Affero General Public License v3
